ezpermissions/__init__.py
ezpermissions/permissions.py
ezpermissions-1.0.0.dist-info/licenses/LICENSE
ezpermissions-1.0.0.dist-info/METADATA
ezpermissions-1.0.0.dist-info/WHEEL
ezpermissions-1.0.0.dist-info/top_level.txt
ezpermissions-1.0.0.dist-info/RECORD
