Metadata-Version: 2.4
Name: ezpermissions
Version: 1.0.0
Summary: A simple permission manager for Discord bots.
Home-page: https://github.com/ibrahims-main/EzPermissions
Author: Ibrahim Mohsin
Author-email: codingstudentbruh@gmail.com
Classifier: Programming Language :: Python :: 3
Classifier: License :: OSI Approved :: MIT License
Classifier: Operating System :: OS Independent
Requires-Python: >=3.8
License-File: LICENSE
Requires-Dist: discord
Dynamic: author
Dynamic: author-email
Dynamic: classifier
Dynamic: description
Dynamic: description-content-type
Dynamic: home-page
Dynamic: license-file
Dynamic: requires-dist
Dynamic: requires-python
Dynamic: summary
